
{
  "Company Overview": {
    "Name": "Radiant Cash Management Services Ltd",
    "Sector": "Miscellaneous",
    "Industry": "Miscellaneous",
    "Business Description": "Incorporated in 2005, Radiant Cash Management Services Ltd is in the business of Cash Logistics Services, Cash Van Operations and related services. Company is an integrated cash logistics player with pan India presence and a network in Tier 2 and Tier 3+ locations. It provides services ranging from secured cash pick-up and delivery, network currency management, and cash-in-transit solutions to efficient cash processing.",
    "Market Position": "Integrated cash logistics player with pan India presence and a network in Tier 2 and Tier 3+ locations."
  },
  "Financial Metrics": {
    "Market Cap": "₹ 811 Cr.",
    "Current Price": "₹ 76.0",
    "High / Low": "₹ 97.1 / ₹ 71.0",
    "Stock P/E": 18.3,
    "Book Value": "₹ 23.6",
    "Dividend Yield": "3.29 %",
    "ROCE": "30.0 %",
    "ROE": "18.8 %",
    "Face Value": "₹ 1.00"
  },
  "Performance Trends": {
    "Quarterly Results": {
      "Sales": [78, 78, 84, 88, 93, 90, 93, 93, 100, 97, 98, 102],
      "Expenses": [61, 61, 63, 66, 70, 69, 74, 80, 83, 83, 81, 85],
      "Operating Profit": [16, 17, 21, 22, 23, 20, 19, 13, 17, 14, 17, 18],
      "OPM %": ["21%", "22%", "26%", "25%", "25%", "23%", "20%", "14%", "17%", "14%", "17%", "17%"],
      "Other Income": [0, 0, 0, 0, 0, 2, 2, 2, 1, 1, 1, 2],
      "Interest": [1, 1, 0, 0, 0, 0, 0, 0, 0, 1, 0, 0],
      "Depreciation": [1, 1, 1, 1, 1, 1, 1, 1, 2, 2, 2, 2],
      "Profit before tax": [15, 15, 21, 21, 22, 21, 19, 14, 16, 13, 15, 17],
      "Tax %": ["24%", "28%", "26%", "28%", "24%", "25%", "26%", "26%", "26%", "28%", "28%", "27%"],
      "Net Profit": [11, 11, 15, 15, 17, 16, 14, 10, 12, 9, 11, 12],
      "EPS in Rs": [1.10, 1.09, 1.51, 1.47, 1.68, 1.46, 1.34, 0.95, 1.13, 0.84, 1.04, 1.15]
    },
    "Annual Results": {
      "Sales": [195, 221, 248, 222, 286, 355, 385, 398],
      "Expenses": [161, 168, 182, 160, 209, 250, 302, 333],
      "Operating Profit": [35, 53, 66, 62, 77, 105, 82, 65],
      "OPM %": ["18%", "24%", "27%", "28%", "27%", "30%", "21%", "16%"],
      "Other Income": [2, 2, 4, 2, 1, 3, 6, 5],
      "Interest": [24, 16, 17, 16, 22, 19, 20, 2],
      "Depreciation": [3, 2, 2, 3, 4, 4, 6, 8],
      "Profit before tax": [9, 36, 50, 45, 52, 84, 62, 61],
      "Tax %": ["40%", "31%", "27%", "28%", "27%", "26%", "26%", null],
      "Net Profit": [5, 25, 36, 32, 38, 63, 45, 44],
      "EPS in Rs": [51.32, 225.39, 328.80, 316.39, 3.77, 5.88, 4.26, 4.16],
      "Dividend Payout %": ["0%", "0%", "0%", "0%", "556%", "34%", "59%", null],
      "Compounded Sales Growth": {
        "10 Years": null,
        "5 Years": "12%",
        "3 Years": "20%",
        "TTM": "8%"
      },
      "Compounded Profit Growth": {
        "10 Years": null,
        "5 Years": "13%",
        "3 Years": "12%",
        "TTM": "-22%"
      },
      "Stock Price CAGR": {
        "10 Years": null,
        "5 Years": null,
        "3 Years": null,
        "1 Year": "-15%"
      },
      "Return on Equity": {
        "10 Years": null,
        "5 Years": "27%",
        "3 Years": "26%",
        "Last Year": "19%"
      }
    }
  },
  "Ratios": {
    "Debtor Days": [70, 88, 79, 115, 100, 72, 73],
    "Inventory Days": null,
    "Days Payable": null,
    "Cash Conversion Cycle": [70, 88, 79, 115, 100, 72, 73],
    "Working Capital Days": [-427, 76, 69, 92, 87, 62, 62],
    "ROCE %": ["53%", "50%", "44%", "48%", "48%", "30%", null]
  },
  "Peer Comparison": {
    "Peers": [
      {"Name": "GMR Airports", "CMP": 78.82, "P/E": 83225.85, "Mar Cap": "Rs.Cr.", "Div Yld": "0.00", "NP Qtr": "-428.77", "Qtr Profit Var": "-318.52", "Sales Qtr": 2495.46, "Qtr Sales Var": 20.93, "ROCE": 6.41},
      {"Name": "SJVN", "CMP": 111.54, "P/E": 47.39, "Mar Cap": 43832.94, "Div Yld": 1.61, "NP Qtr": 439.90, "Qtr Profit Var": 0.06, "Sales Qtr": 1026.25, "Qtr Sales Var": 16.84, "ROCE": 4.99},
      {"Name": "Sagility India", "CMP": 45.17, "P/E": 92.88, "Mar Cap": 21145.56, "Div Yld": "0.00", "NP Qtr": 117.34, "Qtr Profit Var": 235.64, "Sales Qtr": 1325.05, "Qtr Sales Var": 21.11, "ROCE": 4.71},
      {"Name": "International Ge", "CMP": 471.15, "P/E": 62.68, "Mar Cap": 20361.20, "Div Yld": "0.00", "NP Qtr": 98.79, "Qtr Profit Var": null, "Sales Qtr": null, "Qtr Sales Var": null, "ROCE": null},
      {"Name": "Rites", "CMP": 281.00, "P/E": 33.91, "Mar Cap": 13504.97, "Div Yld": 4.09, "NP Qtr": 82.50, "Qtr Profit Var": "-27.85", "Sales Qtr": 540.86, "Qtr Sales Var": "-7.13", "ROCE": 25.36},
      {"Name": "RattanIndia Ent", "CMP": 66.69, "P/E": 12.87, "Mar Cap": 9218.36, "Div Yld": "0.00", "NP Qtr": "-241.59", "Qtr Profit Var": "-227.06", "Sales Qtr": 1800.62, "Qtr Sales Var": 11.52, "ROCE": 2.89},
      {"Name": "CMS Info Systems", "CMP": 490.50, "P/E": 22.22, "Mar Cap": 8004.13, "Div Yld": 1.17, "NP Qtr": 90.92, "Qtr Profit Var": 7.78, "Sales Qtr": 624.54, "Qtr Sales Var": 14.86, "ROCE": 26.95},
      {"Name": "Radiant Cash", "CMP": 76.01, "P/E": 18.27, "Mar Cap": 811.09, "Div Yld": 3.29, "NP Qtr": 12.27, "Qtr Profit Var": 20.65, "Sales Qtr": 102.39, "Qtr Sales Var": 9.54, "ROCE": 30.02}
    ],
    "Median": {
      "CMP": 212.43,
      "P/E": 32.44,
      "Mar Cap": 378.27,
      "Div Yld": 0.0,
      "NP Qtr": 3.4,
      "Qtr Profit Var": 6.41,
      "Sales Qtr": 47.6,
      "Qtr Sales Var": 16.62,
      "ROCE": 13.48
    }
  },
  "Other Insights": {
    "Pros": "Company has a good return on equity (ROE) track record: 3 Years ROE 26.1%\nCompany has been maintaining a healthy dividend payout of 216%",
    "Cons": "The pros and cons are machine generated.\nPros / cons are based on a checklist to highlight important points. Please exercise caution and do your own analysis.",
    "Shareholding Pattern Notes": "* The classifications might have changed from Sep'2022 onwards.  The new XBRL format added more details from Sep'22 onwards.  Classifications such as banks and foreign portfolio investors were not available earlier. The sudden changes in FII or DII can be because of these changes.  Click on the line-items to see the names of individual entities."
  },
  "Balance Sheet": {
    "Equity Capital": [1, 1, 1, 1, 10, 11, 11, 11],
    "Reserves": [55, 104, 118, 126, 130, 219, 243, 241],
    "Borrowings": [20, 18, 21, 14, 29, 29, 33, 42],
    "Other Liabilities": [276, 18, 17, 21, 22, 20, 23, 25],
    "Total Liabilities": [352, 141, 158, 162, 191, 279, 309, 318],
    "Fixed Assets": [8, 5, 8, 11, 14, 13, 34, 33],
    "CWIP": [0, 0, 0, 0, 0, 2, 1, 0],
    "Investments": [0, 33, 28, 0, 0, 0, 11, 11],
    "Other Assets": [344, 103, 121, 151, 176, 264, 263, 274],
    "Total Assets": [352, 141, 158, 162, 191, 279, 309, 318]
  },
  "Cash Flows": {
    "Cash from Operating Activity": [97, 14, 40, 28, 31, 74, 46],
    "Cash from Investing Activity": [0, -24, 6, 26, -2, -74, 9],
    "Cash from Financing Activity": [-14, 20, -22, -37, -12, 26, -26],
    "Net Cash Flow": [84, 10, 24, 16, 16, 27, 29]
  },
  "Shareholding Pattern": {
    "Quarterly": {
      "Promoters": ["56.92%", "56.92%", "56.92%", "56.92%", "56.92%", "56.92%", "56.92%"],
      "FIIs": ["8.03%", "7.56%", "4.95%", "2.13%", "0.13%", "0.07%", "2.15%"],
      "DIIs": ["25.25%", "25.46%", "16.58%", "18.93%", "18.77%", "16.42%", "9.61%"],
      "Public": ["9.80%", "10.08%", "21.54%", "22.01%", "24.18%", "26.60%", "31.33%"]
    },
    "Yearly": {
      "Promoters": ["56.92%", "56.92%", "56.92%"],
      "FIIs": ["8.03%", "0.13%", "2.15%"],
      "DIIs": ["25.25%", "18.77%", "9.61%"],
      "Public": ["9.80%", "24.18%", "31.33%"]
    },
    "No. of Shareholders": [11804, 16642, 30108, 37835, 42282, 42076, 43989]
  },
  "Documents": {
    "Announcements": [
      {"Date": "18 Nov", "Title": "Announcement under Regulation 30 (LODR)-Earnings Call Transcript", "Description": "Transcript of Q2 FY'25 earnings call for RadiantCMS."},
      {"Date": "15 Nov", "Title": "Announcement under Regulation 30 (LODR)-Newspaper Publication", "Description": "Newspaper publication of the financial results for the quarter and six months period ended 30 September 2024"},
      {"Date": "15 Nov", "Title": "Revised Outcome Of Board Meeting - Financial Results", "Description": "Submission of revised financial results for Q2 2024."},
      {"Date": "14 Nov", "Title": "Announcement under Regulation 30 (LODR)-Analyst / Investor Meet - Outcome", "Description": "Outcome of Q2 earnings call recording uploaded."},
      {"Date": "13 Nov", "Title": "Announcement under Regulation 30 (LODR)-Investor Presentation", "Description": "Investor presentation for Q2 earnings call on Nov 14, 2024."}
    ],
    "Annual Reports": [
      {"Year": 2024, "Source": "bse"},
      {"Year": 2023, "Source": "bse"}
    ]
  }
}
