
{
  "Company Overview": {
    "Name": "NTC Industries Ltd",
    "Sector": "Tobacco Products",
    "Industry": "Cigarettes",
    "Business Description": "Incorporated in 1931, NTC industries Ltd manufactures Cigarettes and Smoking Mixtures.  Company is a part of RDB Industries. It does processing of tobacco blends and manufactures packed cigarettes, other tobacco products, etc. which it trades in domestic market and exports to Brussels, Rotterdam, Amsterdam, Paris and Luxemburg. Also, company has a license to manufacture FMCG products",
    "Market Position": "Information not explicitly available in provided HTML."
  },
  "Financial Metrics": {
    "Market Cap": "₹ 349 Cr.",
    "Current Price": "₹ 246",
    "High / Low": "₹ 295 / ₹ 88.0",
    "Stock P/E": "77.9",
    "Book Value": "₹ 120",
    "Dividend Yield": "0.00 %",
    "ROCE": "8.38 %",
    "ROE": "7.29 %",
    "Face Value": "₹ 10.0",
    "Debt-to-Equity Ratio": "Information not explicitly available in provided HTML." 
  },
  "Performance Trends": {
    "Quarterly Results": {
      "Sales": [9.20, 8.42, 7.71, 12.35, 17.72, 9.09, 10.25, 12.14, 10.02, 7.35, 12.61, 7.63, 15.42],
      "Expenses": [6.84, 5.16, 6.73, 9.93, 14.54, 8.59, 8.08, 9.29, 7.84, 5.71, 10.95, 5.18, 12.79],
      "Operating Profit": [2.36, 3.26, 0.98, 2.42, 3.18, 0.50, 2.17, 2.85, 2.18, 1.64, 1.66, 2.45, 2.63],
      "OPM %": [25.65, 38.72, 12.71, 19.60, 17.95, 5.50, 21.17, 23.48, 21.76, 22.31, 13.16, 32.11, 17.06],
      "Other Income": [1.73, 1.32, 1.63, 1.43, 1.30, 1.08, -0.79, 1.86, 1.90, 3.94, -3.06, 0.76, 1.59],
      "Interest": [0.05, 0.07, 0.10, 0.15, 0.10, 0.09, 0.12, 0.09, 0.12, 0.11, 0.13, 0.91, 1.38],
      "Depreciation": [0.51, 0.51, 0.50, 0.50, 0.52, 0.51, 0.51, 0.49, 0.55, 4.23, 0.53, 0.40, 0.40],
      "Profit before tax": [3.53, 4.00, 2.01, 3.20, 3.86, 0.98, 0.75, 4.13, 3.41, 1.24, -2.06, 1.90, 2.44],
      "Tax %": [15.01, 39.25, 23.38, 8.12, 14.51, -24.49, 252.00, 15.74, 13.78, -1.61, 27.18, 19.47, 20.08],
      "Net Profit": [2.99, 2.43, 1.55, 2.94, 3.30, 1.23, -1.14, 3.48, 2.93, 1.26, -2.61, 1.52, 1.95],
      "EPS in Rs": [2.50, 2.03, 1.30, 2.46, 2.76, 1.03, -0.95, 2.91, 2.45, 1.05, -2.19, 1.27, 1.63]
    },
    "Annual Results": {
      "Sales": [31.63, 22.53, 24.54, 18.00, 22.71, 23.78, 21.73, 21.27, 28.79, 31.19, 49.42, 42.13, 43.01],
      "Expenses": [32.52, 19.62, 21.99, 12.64, 16.25, 17.68, 16.89, 19.92, 18.51, 23.12, 42.80, 37.23, 34.63],
      "Operating Profit": [-0.89, 2.91, 2.55, 5.36, 6.46, 6.10, 4.84, 1.35, 10.28, 8.07, 6.62, 4.90, 8.38],
      "OPM %": [-2.81, 12.92, 10.39, 29.78, 28.45, 25.65, 22.27, 6.35, 35.71, 25.87, 13.40, 11.63, 19.48],
      "Other Income": [8.12, 1.23, 1.91, 3.27, 3.79, 2.71, 9.94, 7.46, 4.40, 5.84, 4.67, 4.38, 3.23],
      "Interest": [3.42, 1.05, 0.92, 4.28, 3.32, 2.25, 1.79, 1.30, 0.73, 0.29, 0.46, 0.45, 2.53],
      "Depreciation": [1.70, 1.25, 1.11, 1.81, 1.85, 1.89, 1.89, 1.92, 1.91, 2.04, 2.04, 2.10, 5.56],
      "Profit before tax": [2.11, 1.84, 2.43, 2.54, 5.08, 4.67, 11.10, 5.59, 12.04, 11.58, 8.79, 6.73, 3.52],
      "Tax %": [16.59, 31.52, 4.53, 32.28, 24.80, 21.20, 22.43, 21.29, 33.31, 22.28, 27.99, 24.81, 20.08],
      "Net Profit": [1.52, 1.25, 2.33, 1.72, 3.82, 3.68, 8.62, 4.41, 8.04, 9.01, 6.32, 5.06, 2.12],
      "EPS in Rs": [1.50, 1.16, 2.16, 1.59, 3.54, 3.41, 7.98, 4.08, 6.73, 7.54, 5.29, 4.24, 1.76]
    }
  },
  "Ratios": {
    "Growth Ratios": {
      "Compounded Sales Growth (10 Years)": "6%",
      "Compounded Sales Growth (5 Years)": "14%",
      "Compounded Sales Growth (3 Years)": "14%",
      "Compounded Sales Growth (TTM)": "4%",
      "Compounded Profit Growth (10 Years)": "19%",
      "Compounded Profit Growth (5 Years)": "7%",
      "Compounded Profit Growth (3 Years)": "-5%",
      "Compounded Profit Growth (TTM)": "-31%",
      "Stock Price CAGR (10 Years)": "34%",
      "Stock Price CAGR (5 Years)": "54%",
      "Stock Price CAGR (3 Years)": "30%",
      "Stock Price CAGR (1 Year)": "177%"
    },
    "Liquidity Ratios": {
      "Debtor Days": [114.13, 83.60, 54.59, 27.38, 26.84, 59.86, 49.55, 63.84, 95.34, 73.37, 38.33, 67.75],
      "Inventory Days": [166.92, 129.18, 509.43, 183.99, 120.90, 130.83, 221.81, 373.50, 144.23, 93.24, 124.63],
      "Days Payable": [100.15, 69.97, 222.81, 167.58, 91.94, 42.88, 209.17, 352.72, 55.93, 24.84, 66.28],
      "Cash Conversion Cycle": [114.13, 150.36, 113.79, 314.00, 43.25, 88.82, 137.50, 76.47, 116.11, 161.68, 106.74, 126.10],
      "Working Capital Days": [1281.94, -18.79, 314.88, 430.29, 283.67, 352.57, 504.42, 485.47, 411.15, 591.33, 390.26, 21.40]
    },
    "Profitability Ratios": {
      "ROCE %": [3.34, 5.45, 10.77, 12.89, 13.67, 12.65, 7.76, 18.35, 14.50, 10.03, 8.38],
      "ROE": [9, 9, 9, 7]
    },
    "Valuation Ratios": {
      "P/E": [77.89]
    }
  },
  "Peer Comparison": {
    "Peers": [
      {"Name": "ITC", "CMP": "464.65", "P/E": "28.29", "Mar Cap": "581314.87", "Div Yld": "2.96", "NP Qtr": "5054.43", "Qtr Profit Var": "1.95", "Sales Qtr": "20735.87", "Qtr Sales Var": "16.66", "ROCE": "37.47"},
      {"Name": "Godfrey Phillips", "CMP": "5323.70", "P/E": "29.33", "Mar Cap": "27680.00", "Div Yld": "1.05", "NP Qtr": "248.31", "Qtr Profit Var": "22.89", "Sales Qtr": "1383.98", "Qtr Sales Var": "19.55", "ROCE": "22.17"},
      {"Name": "VST Industries", "CMP": "334.75", "P/E": "23.39", "Mar Cap": "5686.10", "Div Yld": "4.07", "NP Qtr": "47.56", "Qtr Profit Var": "-37.38", "Sales Qtr": "360.03", "Qtr Sales Var": "3.00", "ROCE": "32.24"}
    ],
    "Median": {
      "CMP": "399.7",
      "P/E": "28.81",
      "Mar Cap": "16683.05",
      "Div Yld": "2.0",
      "NP Qtr": "147.94",
      "Qtr Profit Var": "-15.75",
      "Sales Qtr": "872.0",
      "Qtr Sales Var": "18.11",
      "ROCE": "27.21"
    }
  },
  "Other Insights": {
    "Pros": [
      "Company's working capital requirements have reduced from 334 days to 21.4 days"
    ],
    "Cons": [
      "Though the company is reporting repeated profits, it is not paying out dividend",
      "Promoter holding has decreased over last quarter: -10.3%",
      "Company has a low return on equity of 8.63% over last 3 years."
    ],
    "Disclaimer": "The pros and cons are machine generated. Pros / cons are based on a checklist to highlight important points. Please exercise caution and do your own analysis.",
    "Shareholding Pattern Notes": "* The classifications might have changed from Sep'2022 onwards. The new XBRL format added more details from Sep'22 onwards. Classifications such as banks and foreign portfolio investors were not available earlier. The sudden changes in FII or DII can be because of these changes. Click on the line-items to see the names of individual entities."
  },
  "Shareholding Pattern": {
    "Quarterly": {
      "Promoters": [65.90, 65.90, 65.90, 65.90, 65.90, 65.90, 65.90, 65.90, 65.90, 65.90, 66.06, 55.59],
      "FIIs": [4.87, 4.87, 0.02, 0.02, 0.02, 0.02, 0.02, 0.02, 0.02, 0.02, 0.02, 3.18],
      "DIIs": [0.02, 0.02, 0.02, 0.02, 0.02, 0.02, 0.02, 0.02, 0.02, 0.00, 0.00, 0.00],
      "Public": [29.21, 29.21, 34.07, 34.07, 34.08, 34.07, 34.08, 34.06, 34.08, 34.09, 33.93, 41.23]
    },
    "Yearly": {
      "Promoters": [67.47, 67.47, 67.50, 67.50, 70.75, 65.90, 65.90, 65.90, 55.59],
      "FIIs": [0.00, 0.00, 0.00, 0.00, 0.00, 4.87, 0.02, 0.02, 3.18],
      "DIIs": [0.02, 0.02, 0.02, 0.02, 0.02, 0.02, 0.02, 0.02, 0.00],
      "Public": [32.51, 32.51, 32.48, 32.48, 29.23, 29.21, 34.08, 34.08, 41.23]
    }
  },
  "Documents": {
    "Announcements": [
      {"Date": "13 Dec", "Title": "Clarification on loss of share certificate submission."},
      {"Date": "13 Dec", "Title": "Board Meeting Outcome for Conversion And Allotment Of 200000 Warrants Into Equivalent Number Of Equity Shares."},
      {"Date": "6 Dec", "Title": "Allotment of 2,00,000 equity shares on warrant conversion."},
      {"Date": "6 Dec", "Title": "Allotment of 2,00,000 equity shares on warrant conversion."},
      {"Date": "3 Dec", "Title": "Annual reports"}
    ],
    "Annual Reports": [
      "Financial Year 2024",
      "Financial Year 2023",
      "Financial Year 2022",
      "Financial Year 2021",
      "Financial Year 2020",
      "Financial Year 2019",
      "Financial Year 2018",
      "Financial Year 2017",
      "Financial Year 2016",
      "Financial Year 2015",
      "Financial Year 2014",
      "Financial Year 2013",
      "Financial Year 2012",
      "Financial Year 2011",
      "Financial Year 2010"
    ]
  }
}
